mathematica/__init__.py
mathematica/builtins.py
mathematica/lexer.py
mathematica/style.py
pygments_mathematica-0.4.2.dist-info/LICENSE
pygments_mathematica-0.4.2.dist-info/METADATA
pygments_mathematica-0.4.2.dist-info/WHEEL
pygments_mathematica-0.4.2.dist-info/entry_points.txt
pygments_mathematica-0.4.2.dist-info/top_level.txt
pygments_mathematica-0.4.2.dist-info/RECORD
