Metadata-Version: 2.2
Name: pygments-mathematica
Version: 0.4.2
Summary: Mathematica/Wolfram Language Lexer for Pygments
Home-page: http://github.com/rsmenon/pygments-mathematica/
Author: rsmenon
Author-email: rsmenon@icloud.com
License: MIT
Keywords: syntax highlighting mathematica
Platform: any
Classifier: Development Status :: 4 - Beta
Classifier: Intended Audience :: End Users/Desktop
Classifier: License :: OSI Approved :: MIT License
Classifier: Operating System :: OS Independent
Classifier: Programming Language :: Python
Classifier: Programming Language :: Python :: 3.9
Classifier: Programming Language :: Python :: 3.10
Classifier: Programming Language :: Python :: 3.11
Classifier: Programming Language :: Python :: 3.12
Classifier: Programming Language :: Python :: 3.13
Classifier: Topic :: Text Processing
Classifier: Topic :: Utilities
License-File: LICENSE
Requires-Dist: Pygments>=2.19
Dynamic: author
Dynamic: author-email
Dynamic: classifier
Dynamic: description
Dynamic: home-page
Dynamic: keywords
Dynamic: license
Dynamic: platform
Dynamic: requires-dist
Dynamic: summary
